pyedo/__init__.py
pyedo/_info.py
pyedo/edo.py
pyedo/examples/StartUp.py
pyedo/examples/move_cartesianX.py
pyedo/examples/prog_cartesian.py
pyedo/examples/prog_circular.py
pyedo/examples/prog_circularX.py
pyedo/examples/prog_jogjoint.py
pyedo/examples/rodeo.py
pyedocustom-0.11.dist-info/LICENSE
pyedocustom-0.11.dist-info/METADATA
pyedocustom-0.11.dist-info/WHEEL
pyedocustom-0.11.dist-info/top_level.txt
pyedocustom-0.11.dist-info/RECORD
