Metadata-Version: 2.1
Name: pyedocustom
Version: 0.11
Summary: This package contains the SDK to program e.DO robot with Python
Home-page: https://github.com/comau/pyedo
Author: RWS
Author-email: salvatore@rwsdigital.com
Project-URL: Bug Tracker, https://github.com/Comau/pyedo/issues
Classifier: Programming Language :: Python
Classifier: License :: OSI Approved :: GNU General Public License v3 (GPLv3)
Classifier: Operating System :: OS Independent
License-File: LICENSE
